Workbook
Name solver_dua: 1
Name solver_ibd: 2
Name solver_lva: 2
Name solver_ofx: 2
Name solver_pro: 2
Name solver_reo: 2
Name solver_rep: 2
Name solver_tms: 2

Sheet TSMC
B3: TSMC Fixed Location Decision With ABC Products (2/3nm, 5nm, and 7nm)
B7: Transit Cost + Unit Cost per 1,000 Units (Based Upon ABC Products for TSMC)
A8: Unit Costs | B8: A Product(2/3 NM) | H8: B Product(5 NM) | N8: C Product(7 NM) | T8: Associated Costs|Constraint
A9: Fab Location(Cities) | B9: Silicon | C9: Aus | D9: Shz | E9: Seo | F9: Mun | G9: Tok | H9: Silicon | I9: Aus | J9: Shz | K9: Seo | L9: Mun | M9: Tok | N9: Silicon | O9: Aus | P9: Shz | Q9: Seo | R9: Mun | S9: Tok | T9: Fixed Value | U9: Constraint (Per 1,000 bathces) | X9: Key
A10: Hsinchu | B10: =Rates!M8+Rates!M27 -> 20002074 | C10: =Rates!N8+Rates!N27 -> 20002406 | D10: =Rates!O8+Rates!O27 -> 20000794 | E10: =Rates!P8+Rates!P27 -> 20001126 | F10: =Rates!Q8+Rates!Q27 -> 20001920 | G10: =Rates!R8+Rates!R27 -> 20001126 | H10: =Rates!S8+Rates!S27 -> 16002074 | I10: =Rates!T8+Rates!T27 -> 16002406 | ... S10: =Rates!AD8+Rates!AD27 -> 9001126.4 | T10: 12000000000 | U10: =1200000/1000 -> 1200
A11: Tainan | B11: =Rates!M9+Rates!M28 -> 20002074 | C11: =Rates!N9+Rates!N28 -> 20002406 | D11: =Rates!O9+Rates!O28 -> 20000794 | E11: =Rates!P9+Rates!P28 -> 20001126 | F11: =Rates!Q9+Rates!Q28 -> 20001920 | G11: =Rates!R9+Rates!R28 -> 20001126 | H11: =Rates!S9+Rates!S28 -> 16002074 | I11: =Rates!T9+Rates!T28 -> 16002406 | ... S11: =Rates!AD9+Rates!AD28 -> 9001126.4 | T11: 12000000000 | U11: =3000000/1000 -> 3000
A12: Kaohsiung | B12: =Rates!M10+Rates!M29 -> 20002074 | C12: =Rates!N10+Rates!N29 -> 20002406 | D12: =Rates!O10+Rates!O29 -> 20000794 | E12: =Rates!P10+Rates!P29 -> 20001126 | F12: =Rates!Q10+Rates!Q29 -> 20001920 | G12: =Rates!R10+Rates!R29 -> 20001126 | H12: 0 | I12: 0 | J12: 0 | K12: 0 | L12: 0 | M12: 0 | N12: 0 | O12: 0 | P12: 0 | Q12: 0 | R12: 0 | S12: 0 | T12: 45200000000 | U12: =1440000/1000 -> 1440 | X12: All Models Weight Roughly the same
A13: Arizona | B13: =Rates!M11+Rates!M30 -> 26000794 | C13: =Rates!N11+Rates!N30 -> 26000640 | D13: =Rates!O11+Rates!O30 -> 26002253 | E13: =Rates!P11+Rates!P30 -> 26002074 | F13: =Rates!Q11+Rates!Q30 -> 26001920 | G13: =Rates!R11+Rates!R30 -> 26001920 | H13: =Rates!S11+Rates!S30 -> 20800794 | I13: =Rates!T11+Rates!T30 -> 20800640 | ... M13: =Rates!X11+Rates!X30 -> 20801920 | N13: 0 | O13: 0 | P13: 0 | Q13: 0 | R13: 0 | S13: 0 | T13: 65000000000 | U13: 720
A14: Taichung | B14: 0 | C14: 0 | D14: 0 | E14: 0 | F14: 0 | G14: 0 | H14: =Rates!S12+Rates!S31 -> 16002074 | I14: =Rates!T12+Rates!T31 -> 16002406 | J14: =Rates!U12+Rates!U31 -> 16000794 | K14: =Rates!V12+Rates!V31 -> 16001126 | L14: =Rates!W12+Rates!W31 -> 16001920 | M14: =Rates!X12+Rates!X31 -> 16001126 | N14: =Rates!Y12+Rates!Y31 -> 9002073.6 | O14: =Rates!Z12+Rates!Z31 -> 9002406.4 | ... S14: =Rates!AD12+Rates!AD31 -> 9001126.4 | T14: 12000000000 | U14: 1200 | X14: EQ=.125KG*100000
A15: Japan | B15: 0 | C15: 0 | D15: 0 | E15: 0 | F15: 0 | G15: 0 | H15: 0 | I15: 0 | J15: 0 | K15: 0 | L15: 0 | M15: 0 | N15: 0 | O15: 0 | P15: 0 | Q15: 0 | R15: 0 | S15: 0 | T15: 24000000000 | U15: 360
A16: TOTAL Demand | B16: {=TRANSPOSE(Rates!C30:C35)/1000} -> 425 | C16: 425 | D16: 1275 | E16: 1487.5 | F16: 425 | G16: 212.5 | H16: {=TRANSPOSE(Rates!D30:D35)/1000} -> 612 | I16: 612 | J16: 1836 | K16: 2142 | L16: 612 | M16: 306 | N16: {=TRANSPOSE(Rates!E30:E35)/1000} -> 221 | O16: 221 | P16: 663 | Q16: 773.5 | R16: 221 | S16: 110.5 | X16: 1 Batch assumed Per 1,000 Wafer
E18: Cost Per Unit 1,000 (Based Upon ABC Products for TSMC) | X18: Not all Demand meant Due to Capacity
A19: Decision Point | B19: A Product(2/3 NM) | H19: B Product(5 NM) | N19: C Product(7 NM) | T19: Location Variable | U19: SUM Units Used per (1,000)
A20: Fab Location(Cities) | B20: Silicon | C20: Aus | D20: Shz | E20: Seo | F20: Mun | G20: Tok | H20: Silicon | I20: Aus | J20: Shz | K20: Seo | L20: Mun | M20: Tok | N20: Silicon | O20: Aus | P20: Shz | Q20: Seo | R20: Mun | S20: Tok | T20: 1 or 0 | X20: ABC Products Make up or 74% of Revenue
A21: Hsinchu | B21: 0 | C21: 0 | D21: 0 | E21: 0 | F21: 0 | G21: 0 | H21: 0 | I21: 0 | J21: 1200 | K21: 0 | L21: 0 | M21: 0 | N21: 0 | O21: 0 | P21: 0 | Q21: 0 | R21: 0 | S21: 0 | T21: 1 | U21: =SUM(B21:S21) -> 1200
A22: Tainan | B22: 0 | C22: 0 | D22: 0 | E22: 0 | F22: 0 | G22: 0 | H22: 0 | I22: 0 | J22: 636 | K22: 264.5 | L22: 0 | M22: 0 | N22: 221 | O22: 221 | P22: 663 | Q22: 773.5 | R22: 221 | S22: 0 | T22: 1 | U22: =SUM(B22:S22) -> 3000 | Y22: Means not able to be made at Site
A23: Kaohsiung | B23: 0 | C23: 0 | D23: 0 | E23: 0 | F23: 0 | G23: 0 | H23: 0 | I23: 0 | J23: 0 | K23: 0 | L23: 0 | M23: 0 | N23: 0 | O23: 0 | P23: 0 | Q23: 0 | R23: 0 | S23: 0 | T23: 0 | U23: =SUM(B23:S23) -> 0
A24: Arizona | B24: 0 | C24: 0 | D24: 0 | E24: 0 | F24: 0 | G24: 0 | H24: 0 | I24: 0 | J24: 0 | K24: 0 | L24: 0 | M24: 0 | N24: 0 | O24: 0 | P24: 0 | Q24: 0 | R24: 0 | S24: 0 | T24: 0 | U24: =SUM(B24:S24) -> 0 | X24: Products 2/3nm, 5 nm, and 7nm
A25: Taichung | B25: 0 | C25: 0 | D25: 0 | E25: 0 | F25: 0 | G25: 0 | H25: 0 | I25: 0 | J25: 0 | K25: 1089.5 | L25: 0 | M25: 0 | N25: 0 | O25: 0 | P25: 0 | Q25: 0 | R25: 0 | S25: 110.5 | T25: 1 | U25: =SUM(B25:S25) -> 1200
A26: Japan | B26: 0 | C26: 0 | D26: 0 | E26: 0 | F26: 0 | G26: 0 | H26: 0 | I26: 0 | J26: 0 | K26: 0 | L26: 0 | M26: 0 | N26: 0 | O26: 0 | P26: 0 | Q26: 0 | R26: 0 | S26: 0 | T26: 0 | U26: =SUM(B26:S26) -> 0 | X26: 30000000 | Y26: Penalty Cost for Unmet Demand
E28: Excess/Constraints Per Unit 1,000 (Based Upon ABC Products for TSMC)
A29: Constrains | B29: A Product(2/3 NM) | H29: B Product(5 NM) | N29: C Product(7 NM)
A30: Fab Location(Cities) | B30: Silicon | C30: Aus | D30: Shz | E30: Seo | F30: Mun | G30: Tok | H30: Silicon | I30: Aus | J30: Shz | K30: Seo | L30: Mun | M30: Tok | N30: Silicon | O30: Aus | P30: Shz | Q30: Seo | R30: Mun | S30: Tok
A31: Hsinchu | B31: =$U$10*$T$21-SUM($B$21:$S$21) -> 0
A32: Tainan | B32: =$U$11*$T$22-SUM($B$22:$S$22) -> 0
A33: Kaohsiung | B33: =$U$12*$T$23-SUM($B$23:$S$23) -> 0
A34: Arizona | B34: =$U$13*$T$24-SUM($B$24:$S$24) -> 0
A35: Taichung | B35: =$U$14*$T$25-SUM($B$25:$S$25) -> 0
A36: Japan | B36: =$U$15*$T$26-SUM($B$26:$S$26) -> 0
A37: Excess Demand | B37: =B16-SUM(B21:B26) -> 425 | C37: =C16-SUM(C21:C26) -> 425 | D37: =D16-SUM(D21:D26) -> 1275 | E37: =E16-SUM(E21:E26) -> 1487.5 | F37: =F16-SUM(F21:F26) -> 425 | G37: =G16-SUM(G21:G26) -> 212.5 | H37: =H16-SUM(H21:H26) -> 612 | I37: =I16-SUM(I21:I26) -> 612 | ... S37: =S16-SUM(S21:S26) -> 0
B42: Results ( In Units Per 1,000 wafers)
C45: Total Fixed Costs | D45: Total Variable Cost | E45: Penalty Cost | F45: Costs All together | H45: Demand | I45: Opened Capacity | J45: Total Available Capacity | K45: Unmet Demand
C46: =SUMPRODUCT(T10:T15,T21:T26) -> 36000000000 | D46: =SUMPRODUCT(B21:S26,B10:S15) -> 7.0935918e+10 | E46: =SUM(B37:S37)*X26 -> 215400000000 | F46: =SUM(C46:E46) -> 3.2233592e+11 | H46: =SUM(B16:S16) -> 12580 | I46: =SUMPRODUCT(T21:T26,U10:U15) -> 5400 | J46: =SUM(U10:U15) -> 7920 | K46: =SUM(B37:S37) -> 7180
F57: ss

Sheet Rates
A2: Baseline Information | O2: Node Matrix Application
A4: Transit Rate Tables - Per Site (Saudi Market + Freightos estimates)
A5: Batch Size | B5: 1000
A6: Unit weight (kg/wafer): | B6: 0.32 | C6: According to resources | L6: Transport Matrix | M6: A Product(2/3 NM) | S6: B Product(5 NM) | Y6: C Product(7 NM) | AE6: Associated Costs|Constraint
A7: Batch weight (kg per 100,000): | B7: 320 | L7: Fab Location(Cities) | M7: Silicon | N7: Aus | O7: Shz | P7: Seo | Q7: Mun | R7: Tok | S7: Silicon | T7: Aus | U7: Shz | V7: Seo | W7: Mun | X7: Tok | Y7: Silicon | Z7: Aus | AA7: Shz | AB7: Seo | AC7: Mun | AD7: Tok | AE7: Fixed Value (Billions) | AF7: Constraint (Millions)
A8: Cost per 1,000 wafers = Rate(B5) x Batch Weight(B6). Batch = 1,000 wafers = 40 FOUPs = 320 kg (8 kg/loaded 25-wafer FOUP, per Wikipedia/Entegris/Semitracks). Est., not TSMC contract rates.- This is our Assumptions* | L8: Hsinchu | M8: {=TRANSPOSE($C$44:$C$49)} -> 2073.6 | N8: 2406.4 | O8: 793.6 | P8: 1126.4 | Q8: 1920 | R8: 1126.4 | S8: {=TRANSPOSE($C$44:$C$49)} -> 2073.6 | T8: 2406.4 | U8: 793.6 | V8: 1126.4 | W8: 1920 | X8: 1126.4 | Y8: {=TRANSPOSE($C$44:$C$49)} -> 2073.6 | Z8: 2406.4 | AA8: 793.6 | AB8: 1126.4 | AC8: 1920 | AD8: 1126.4 | AE8: 12 | AF8: 1.2
L9: Tainan | M9: {=TRANSPOSE($C$44:$C$49)} -> 2073.6 | N9: 2406.4 | O9: 793.6 | P9: 1126.4 | Q9: 1920 | R9: 1126.4 | S9: {=TRANSPOSE($C$44:$C$49)} -> 2073.6 | T9: 2406.4 | U9: 793.6 | V9: 1126.4 | W9: 1920 | X9: 1126.4 | Y9: {=TRANSPOSE($C$44:$C$49)} -> 2073.6 | Z9: 2406.4 | AA9: 793.6 | AB9: 1126.4 | AC9: 1920 | AD9: 1126.4 | AE9: 12 | AF9: 3
A10: Baseline Assumptions | L10: Kaohsiung | M10: {=TRANSPOSE($C$44:$C$49)} -> 2073.6 | N10: 2406.4 | O10: 793.6 | P10: 1126.4 | Q10: 1920 | R10: 1126.4 | AE10: 9.49 | AF10: 1.44
L11: Arizona | M11: {=TRANSPOSE($C$71:$C$76)} -> 793.6 | N11: 640 | O11: 2252.8 | P11: 2073.6 | Q11: 1920 | R11: 1920 | S11: {=TRANSPOSE($C$71:$C$76)} -> 793.6 | T11: 640 | U11: 2252.8 | V11: 2073.6 | W11: 1920 | X11: 1920 | AE11: 65 | AF11: 0.72
A12: Country Premium | L12: Taichung | S12: {=TRANSPOSE($C$44:$C$49)} -> 2073.6 | T12: 2406.4 | U12: 793.6 | V12: 1126.4 | W12: 1920 | X12: 1126.4 | Y12: {=TRANSPOSE($C$44:$C$49)} -> 2073.6 | Z12: 2406.4 | AA12: 793.6 | AB12: 1126.4 | AC12: 1920 | AD12: 1126.4 | AE12: 2.87 | AF12: 1.2
A13: Country | B13: USA | C13: JPN | L13: Japan | AE13: 24 | AF13: 1.2
A14: Rates | B14: =D71/D44 -> 1.3 | C14: =E89/E53 -> 1.2 | L14: TOTAL Demand | M14: =TSMC!B16 -> 425 | N14: =TSMC!C16 -> 425 | O14: =TSMC!D16 -> 1275 | P14: =TSMC!E16 -> 1487.5 | Q14: =TSMC!F16 -> 425 | R14: =TSMC!G16 -> 212.5 | S14: =TSMC!H16 -> 612 | T14: =TSMC!I16 -> 612 | ... AD14: =TSMC!S16 -> 110.5
A16: Cost Assumptions Per Wafer
A18: A Cost | B18: B Cost | C18: C Cost
A19: 20000 | B19: 16000 | C19: 9000
A22: Demand Forecast
A23: DEMAND (300mm wafers / year) | D23: Taiwan Semi- ABC~74.5(Multiply by Ratio) | F23: =1/0.74 -> 1.3513514
A24: Global total wafers (TSMC Website): | B24: 17000000 | C24: ABC Total | D24: =B24*0.74 -> 12580000
A25: A=below3nm, B=5nm, C=7nm | C25: =0.25 -> 0.25 | D25: 0.36 | E25: 0.13 | F25: ~Note this is 74% of prdouct mix | L25: Product Cost Matrix | M25: A Product(2/3 NM) | S25: B Product(5 NM) | Y25: C Product(7 NM)
L26: Fab Location(Cities) | M26: Silicon | N26: Aus | O26: Shz | P26: Seo | Q26: Mun | R26: Tok | S26: Silicon | T26: Aus | U26: Shz | V26: Seo | W26: Mun | X26: Tok | Y26: Silicon | Z26: Aus | AA26: Shz | AB26: Seo | AC26: Mun | AD26: Tok
A27: Demand Forecast Allocation | L27: Hsinchu | M27: =A$19*1000 -> 20000000 | N27: =A$19*1000 -> 20000000 | O27: =A$19*1000 -> 20000000 | P27: =A$19*1000 -> 20000000 | Q27: =A$19*1000 -> 20000000 | R27: =A$19*1000 -> 20000000 | S27: {=TRANSPOSE($E44:E49)} -> 16000000 | T27: 16000000 | U27: 16000000 | V27: 16000000 | W27: 16000000 | X27: 16000000 | Y27: {=TRANSPOSE(F44:F49)} -> 9000000 | Z27: 9000000 | AA27: 9000000 | AB27: 9000000 | AC27: 9000000 | AD27: 9000000
A28: Per City Allocation (W/Ratio) | C28: =C25*$F$23 -> 0.33783784 | D28: =D25*$F$23 -> 0.48648649 | E28: =E25*$F$23 -> 0.17567568 | L28: Tainan | M28: =A$19*1000 -> 20000000 | N28: =A$19*1000 -> 20000000 | O28: =A$19*1000 -> 20000000 | P28: =A$19*1000 -> 20000000 | Q28: =A$19*1000 -> 20000000 | R28: =A$19*1000 -> 20000000 | S28: {=TRANSPOSE($E44:E49)} -> 16000000 | T28: 16000000 | U28: 16000000 | V28: 16000000 | W28: 16000000 | X28: 16000000 | Y28: {=TRANSPOSE(F44:F49)} -> 9000000 | Z28: 9000000 | AA28: 9000000 | AB28: 9000000 | AC28: 9000000 | AD28: 9000000
A29: City | B29: Share | C29: Product A | D29: Product B | E29: Product C | L29: Kaohsiung | M29: =A$19*1000 -> 20000000 | N29: =A$19*1000 -> 20000000 | O29: =A$19*1000 -> 20000000 | P29: =A$19*1000 -> 20000000 | Q29: =A$19*1000 -> 20000000 | R29: =A$19*1000 -> 20000000
A30: Silicon Valley | B30: 0.1 | C30: =ROUND($D$24*C$28*$B30,0) -> 425000 | D30: =ROUND($D$24*D$28*$B30,0) -> 612000 | E30: =ROUND($D$24*E$28*$B30,0) -> 221000 | L30: Arizona | M30: {=TRANSPOSE(D71:D76)} -> 26000000 | N30: 26000000 | O30: 26000000 | P30: 26000000 | Q30: 26000000 | R30: 26000000 | S30: {=TRANSPOSE(E71:E76)} -> 20800000 | T30: 20800000 | U30: 20800000 | V30: 20800000 | W30: 20800000 | X30: 20800000
A31: Austin | B31: 0.1 | C31: =ROUND($D$24*C$28*$B31,0) -> 425000 | D31: =ROUND($D$24*D$28*$B31,0) -> 612000 | E31: =ROUND($D$24*E$28*$B31,0) -> 221000 | L31: Taichung | S31: {=TRANSPOSE(E44:E49)} -> 16000000 | T31: 16000000 | U31: 16000000 | V31: 16000000 | W31: 16000000 | X31: 16000000 | Y31: {=TRANSPOSE(F44:F49)} -> 9000000 | Z31: 9000000 | AA31: 9000000 | AB31: 9000000 | AC31: 9000000 | AD31: 9000000
A32: Shenzhen | B32: 0.3 | C32: =ROUND($D$24*C$28*$B32,0) -> 1275000 | D32: =ROUND($D$24*D$28*$B32,0) -> 1836000 | E32: =ROUND($D$24*E$28*$B32,0) -> 663000 | L32: Japan
A33: Seoul | B33: 0.35 | C33: =ROUND($D$24*C$28*$B33,0) -> 1487500 | D33: =ROUND($D$24*D$28*$B33,0) -> 2142000 | E33: =ROUND($D$24*E$28*$B33,0) -> 773500
A34: Munich | B34: 0.1 | C34: =ROUND($D$24*C$28*$B34,0) -> 425000 | D34: =ROUND($D$24*D$28*$B34,0) -> 612000 | E34: =ROUND($D$24*E$28*$B34,0) -> 221000
A35: Tokyo | B35: 0.05 | C35: =ROUND($D$24*C$28*$B35,0) -> 212500 | D35: =ROUND($D$24*D$28*$B35,0) -> 306000 | E35: =ROUND($D$24*E$28*$B35,0) -> 110500
A36: TOTAL | B36: =SUM(B30:B35) -> 1 | C36: =SUM(C30:C35) -> 4250000 | D36: =SUM(D30:D35) -> 6120000 | E36: =SUM(E30:E35) -> 2210000 | F36: =SUM(C36:E36) -> 12580000 | G36: Total Demand
A37: Node Application
A42: HSINCHU (Taiwan) - makes A, B, C | B42: Shipping | D42: Product Cost to Make | G42: Total Costs
A43: Destination | B43: Rate ($/kg) | C43: Cost per 1,000 | D43: A | E43: B | F43: C | G43: Total Variable A | H43: Total Variable B | I43: Total Variable C
A44: Silicon Valley | B44: 6.48 | C44: =B44*$B$7 -> 2073.6 | D44: =A$19*$B$5 -> 20000000 | E44: =B$19*$B$5 -> 16000000 | F44: =C$19*$B$5 -> 9000000 | G44: =$C44+D44 -> 20002074 | H44: =$C44+E44 -> 16002074 | I44: =$C44+F44 -> 9002073.6
A45: Austin | B45: 7.52 | C45: =B45*$B$7 -> 2406.4 | D45: =A$19*$B$5 -> 20000000 | E45: =B$19*$B$5 -> 16000000 | F45: =C$19*$B$5 -> 9000000 | G45: =$C45+D45 -> 20002406 | H45: =$C45+E45 -> 16002406 | I45: =$C45+F45 -> 9002406.4
A46: Shenzhen | B46: 2.48 | C46: =B46*$B$7 -> 793.6 | D46: =A$19*$B$5 -> 20000000 | E46: =B$19*$B$5 -> 16000000 | F46: =C$19*$B$5 -> 9000000 | G46: =$C46+D46 -> 20000794 | H46: =$C46+E46 -> 16000794 | I46: =$C46+F46 -> 9000793.6
A47: Seoul | B47: 3.52 | C47: =B47*$B$7 -> 1126.4 | D47: =A$19*$B$5 -> 20000000 | E47: =B$19*$B$5 -> 16000000 | F47: =C$19*$B$5 -> 9000000 | G47: =$C47+D47 -> 20001126 | H47: =$C47+E47 -> 16001126 | I47: =$C47+F47 -> 9001126.4
A48: Munich | B48: 6 | C48: =B48*$B$7 -> 1920 | D48: =A$19*$B$5 -> 20000000 | E48: =B$19*$B$5 -> 16000000 | F48: =C$19*$B$5 -> 9000000 | G48: =$C48+D48 -> 20001920 | H48: =$C48+E48 -> 16001920 | I48: =$C48+F48 -> 9001920
A49: Tokyo | B49: 3.52 | C49: =B49*$B$7 -> 1126.4 | D49: =A$19*$B$5 -> 20000000 | E49: =B$19*$B$5 -> 16000000 | F49: =C$19*$B$5 -> 9000000 | G49: =$C49+D49 -> 20001126 | H49: =$C49+E49 -> 16001126 | I49: =$C49+F49 -> 9001126.4
A51: TAINAN (Taiwan) - makes A, B, C
A52: Destination | B52: Rate ($/kg) | C52: Cost per 1,000
A53: Silicon Valley | B53: 6.48 | C53: =B53*$B$7 -> 2073.6 | D53: =A$19*$B$5 -> 20000000 | E53: =B$19*$B$5 -> 16000000 | F53: =C$19*$B$5 -> 9000000 | G53: =$C53+D53 -> 20002074 | H53: =$C53+E53 -> 16002074 | I53: =$C53+F53 -> 9002073.6
A54: Austin | B54: 7.52 | C54: =B54*$B$7 -> 2406.4 | D54: =A$19*$B$5 -> 20000000 | E54: =B$19*$B$5 -> 16000000 | F54: =C$19*$B$5 -> 9000000 | G54: =$C54+D54 -> 20002406 | H54: =$C54+E54 -> 16002406 | I54: =$C54+F54 -> 9002406.4
A55: Shenzhen | B55: 2.48 | C55: =B55*$B$7 -> 793.6 | D55: =A$19*$B$5 -> 20000000 | E55: =B$19*$B$5 -> 16000000 | F55: =C$19*$B$5 -> 9000000 | G55: =$C55+D55 -> 20000794 | H55: =$C55+E55 -> 16000794 | I55: =$C55+F55 -> 9000793.6
A56: Seoul | B56: 3.52 | C56: =B56*$B$7 -> 1126.4 | D56: =A$19*$B$5 -> 20000000 | E56: =B$19*$B$5 -> 16000000 | F56: =C$19*$B$5 -> 9000000 | G56: =$C56+D56 -> 20001126 | H56: =$C56+E56 -> 16001126 | I56: =$C56+F56 -> 9001126.4
A57: Munich | B57: 6 | C57: =B57*$B$7 -> 1920 | D57: =A$19*$B$5 -> 20000000 | E57: =B$19*$B$5 -> 16000000 | F57: =C$19*$B$5 -> 9000000 | G57: =$C57+D57 -> 20001920 | H57: =$C57+E57 -> 16001920 | I57: =$C57+F57 -> 9001920
A58: Tokyo | B58: 3.52 | C58: =B58*$B$7 -> 1126.4 | D58: =A$19*$B$5 -> 20000000 | E58: =B$19*$B$5 -> 16000000 | F58: =C$19*$B$5 -> 9000000 | G58: =$C58+D58 -> 20001126 | H58: =$C58+E58 -> 16001126 | I58: =$C58+F58 -> 9001126.4
A60: KAOHSIUNG (Taiwan) - makes A
A61: Destination | B61: Rate ($/kg) | C61: Cost per 1,000
A62: Silicon Valley | B62: 6.48 | C62: =B62*$B$7 -> 2073.6 | D62: =A$19*$B$5 -> 20000000 | G62: =$C62+D62 -> 20002074
A63: Austin | B63: 7.52 | C63: =B63*$B$7 -> 2406.4 | D63: =A$19*$B$5 -> 20000000 | G63: =$C63+D63 -> 20002406
A64: Shenzhen | B64: 2.48 | C64: =B64*$B$7 -> 793.6 | D64: =A$19*$B$5 -> 20000000 | G64: =$C64+D64 -> 20000794
A65: Seoul | B65: 3.52 | C65: =B65*$B$7 -> 1126.4 | D65: =A$19*$B$5 -> 20000000 | G65: =$C65+D65 -> 20001126
A66: Munich | B66: 6 | C66: =B66*$B$7 -> 1920 | D66: =A$19*$B$5 -> 20000000 | G66: =$C66+D66 -> 20001920
A67: Tokyo | B67: 3.52 | C67: =B67*$B$7 -> 1126.4 | D67: =A$19*$B$5 -> 20000000 | G67: =$C67+D67 -> 20001126
A69: ARIZONA (US) - makes A, B
A70: Destination | B70: Rate ($/kg) | C70: Cost per 1,000
A71: Silicon Valley | B71: 2.48 | C71: =B71*$B$7 -> 793.6 | D71: =D53*1.3 -> 26000000 | E71: =E53*1.3 -> 20800000 | G71: =$C71+D71 -> 26000794 | H71: =$C71+E71 -> 20800794
A72: Austin | B72: 2 | C72: =B72*$B$7 -> 640 | D72: =D54*1.3 -> 26000000 | E72: =E54*1.3 -> 20800000 | G72: =$C72+D72 -> 26000640 | H72: =$C72+E72 -> 20800640
A73: Shenzhen | B73: 7.04 | C73: =B73*$B$7 -> 2252.8 | D73: =D55*1.3 -> 26000000 | E73: =E55*1.3 -> 20800000 | G73: =$C73+D73 -> 26002253 | H73: =$C73+E73 -> 20802253
A74: Seoul | B74: 6.48 | C74: =B74*$B$7 -> 2073.6 | D74: =D56*1.3 -> 26000000 | E74: =E56*1.3 -> 20800000 | G74: =$C74+D74 -> 26002074 | H74: =$C74+E74 -> 20802074
A75: Munich | B75: 6 | C75: =B75*$B$7 -> 1920 | D75: =D57*1.3 -> 26000000 | E75: =E57*1.3 -> 20800000 | G75: =$C75+D75 -> 26001920 | H75: =$C75+E75 -> 20801920
A76: Tokyo | B76: 6 | C76: =B76*$B$7 -> 1920 | D76: =D58*1.3 -> 26000000 | E76: =E58*1.3 -> 20800000 | G76: =$C76+D76 -> 26001920 | H76: =$C76+E76 -> 20801920
A78: Taichung - makes B,C
A79: Destination | B79: Rate ($/kg) | C79: Cost per 1,000
A80: Silicon Valley | B80: 6.48 | C80: =B80*$B$7 -> 2073.6 | E80: =B$19*$B$5 -> 16000000 | F80: =C$19*$B$5 -> 9000000 | H80: =$C80+E80 -> 16002074 | I80: =$C80+F80 -> 9002073.6
A81: Austin | B81: 7.52 | C81: =B81*$B$7 -> 2406.4 | E81: =B$19*$B$5 -> 16000000 | F81: =C$19*$B$5 -> 9000000 | H81: =$C81+E81 -> 16002406 | I81: =$C81+F81 -> 9002406.4
A82: Shenzhen | B82: 2.48 | C82: =B82*$B$7 -> 793.6 | E82: =B$19*$B$5 -> 16000000 | F82: =C$19*$B$5 -> 9000000 | H82: =$C82+E82 -> 16000794 | I82: =$C82+F82 -> 9000793.6
A83: Seoul | B83: 3.52 | C83: =B83*$B$7 -> 1126.4 | E83: =B$19*$B$5 -> 16000000 | F83: =C$19*$B$5 -> 9000000 | H83: =$C83+E83 -> 16001126 | I83: =$C83+F83 -> 9001126.4
A84: Munich | B84: 6 | C84: =B84*$B$7 -> 1920 | E84: =B$19*$B$5 -> 16000000 | F84: =C$19*$B$5 -> 9000000 | H84: =$C84+E84 -> 16001920 | I84: =$C84+F84 -> 9001920
A85: Tokyo | B85: 3.52 | C85: =B85*$B$7 -> 1126.4 | E85: =B$19*$B$5 -> 16000000 | F85: =C$19*$B$5 -> 9000000 | H85: =$C85+E85 -> 16001126 | I85: =$C85+F85 -> 9001126.4
A87: JAPAN - makes A, B, C- Note that this cannot be made right now but it is important to know that this is a good alternative for the future
A88: Destination | B88: Rate ($/kg) | C88: Cost per 1,000
A89: Silicon Valley | B89: 6.48 | C89: =B89*$B$7 -> 2073.6 | D89: =D53*1.2 -> 24000000 | E89: =E53*1.2 -> 19200000 | F89: =$F53*1.2 -> 10800000 | G89: =$C89+D89 -> 24002074 | H89: =$C89+E89 -> 19202074 | I89: =$C89+F89 -> 10802074
A90: Austin | B90: 7.52 | C90: =B90*$B$7 -> 2406.4 | D90: =D54*1.2 -> 24000000 | E90: =E54*1.2 -> 19200000 | F90: =$F54*1.2 -> 10800000 | G90: =$C90+D90 -> 24002406 | H90: =$C90+E90 -> 19202406 | I90: =$C90+F90 -> 10802406
A91: Shenzhen | B91: 3.04 | C91: =B91*$B$7 -> 972.8 | D91: =D55*1.2 -> 24000000 | E91: =E55*1.2 -> 19200000 | F91: =$F55*1.2 -> 10800000 | G91: =$C91+D91 -> 24000973 | H91: =$C91+E91 -> 19200973 | I91: =$C91+F91 -> 10800973
A92: Seoul | B92: 2.48 | C92: =B92*$B$7 -> 793.6 | D92: =D56*1.2 -> 24000000 | E92: =E56*1.2 -> 19200000 | F92: =$F56*1.2 -> 10800000 | G92: =$C92+D92 -> 24000794 | H92: =$C92+E92 -> 19200794 | I92: =$C92+F92 -> 10800794
A93: Munich | B93: 6 | C93: =B93*$B$7 -> 1920 | D93: =D57*1.2 -> 24000000 | E93: =E57*1.2 -> 19200000 | F93: =$F57*1.2 -> 10800000 | G93: =$C93+D93 -> 24001920 | H93: =$C93+E93 -> 19201920 | I93: =$C93+F93 -> 10801920
A94: Tokyo | B94: 1.52 | C94: =B94*$B$7 -> 486.4 | D94: =D58*1.2 -> 24000000 | E94: =E58*1.2 -> 19200000 | F94: =$F58*1.2 -> 10800000 | G94: =$C94+D94 -> 24000486 | H94: =$C94+E94 -> 19200486 | I94: =$C94+F94 -> 10800486
A100: Links For Info and Resources
A102: Revenue-> Demand | B102: https://investor.tsmc.com/english/encrypt/files/encrypt_file/reports/2026-04/a7e3abe65a3fbc342aa55f9f53a5490dd621c1ac/1Q26%20Presentation%20%28E%29.pdf
A103: 17 Million wafers | B103: https://www.tsmc.com/english/dedicatedFoundry/manufacturing/fab_capacity
A104: Wafer Price | B104: https://siliconanalysts.com/guide/semiconductor-costs
A105: Air Frieght | B105: https://suaidglobal.com/insights/air-freight-cost-per-kg/
A106: Air Frieght | B106: https://www.freightos.com/freight-resources/freight-rate-free-calculator/
